{
    "page_2": [
        {
            "url": "https://www.theguardian.com/world/2018/jan/15/me-too-founder-tarana-burke-women-sexual-assault", 
            "title": "Me Too founder Tarana Burke: 'You have to use your privilege to serve ...https://www.theguardian.com/.../me-too-founder-tarana-burke-women-sexual-assault"
        }, 
        {
            "url": "https://www.theatlantic.com/entertainment/archive/2017/10/the-movement-of-metoo/542979/", 
            "title": "The Movement of #MeToo - The Atlantichttps://www.theatlantic.com/entertainment/archive/2017/10/the...of-metoo/542979/"
        }, 
        {
            "url": "https://www.metooshoes.com/", 
            "title": "Me Too Shoes | Feminine and Comfortable Women's Flats, Sandals ...https://www.metooshoes.com/"
        }, 
        {
            "url": "https://www.youtube.com/watch?v=PjpO4hc6Hiw", 
            "title": "Sean Penn Talks His TV Debut, Criticizes #MeToo Movement | TODAY ...https://www.youtube.com/watch?v=PjpO4hc6Hiw"
        }, 
        {
            "url": "https://www.youtube.com/watch?v=qDRORgoZxZU", 
            "title": "Meghan Trainor - Me Too - YouTubehttps://www.youtube.com/watch?v=qDRORgoZxZU"
        }, 
        {
            "url": "http://www.womensmediacenter.com/reports/media-and-metoo-how-a-movement-affected-press-coverage-of-sexual-assault", 
            "title": "Media and #MeToo: How a movement affected press coverage of ...www.womensmediacenter.com/.../media-and-metoo-how-a-movement-affected-press-..."
        }, 
        {
            "url": "https://www.cnn.com/2017/10/17/us/me-too-tarana-burke-origin-trnd/index.html", 
            "title": "#MeToo: An activist, a little girl and the heartbreaking origin of 'Me too ...https://www.cnn.com/2017/10/17/us/me-too-tarana-burke-origin-trnd/index.html"
        }, 
        {
            "url": "https://www.politico.com/magazine/story/2018/10/02/kavanaugh-hearings-me-too-220840", 
            "title": "The Kavanaugh Hearings Are Hurting #MeToo - POLITICO Magazinehttps://www.politico.com/magazine/story/2018/.../kavanaugh-hearings-me-too-22084..."
        }, 
        {
            "url": "https://thehill.com/opinion/civil-rights/408882-how-the-elite-hijacked-the-metoo-movement", 
            "title": "How the elite hijacked the #MeToo movement | TheHillhttps://thehill.com/opinion/civil.../408882-how-the-elite-hijacked-the-metoo-moveme..."
        }, 
        {
            "url": "https://www.theverge.com/2018/1/15/16893734/metoo-movement-backlash", 
            "title": "Forget the backlash \u2014 we need #MeToo now more than ever - The ...https://www.theverge.com/2018/1/15/16893734/metoo-movement-backlash"
        }
    ], 
    "page_3": [
        {
            "url": "https://www.thecut.com/2018/09/unreckoned-left-behind-by-metoo.html", 
            "title": "17 Women Talk About Being Left Behind by #MeToo - The Cuthttps://www.thecut.com/2018/09/unreckoned-left-behind-by-metoo.html"
        }, 
        {
            "url": "https://www.washingtonpost.com/opinions/to-the-president-metoo-is-little-more-than-a-punchline/2018/07/06/7e3d4d3a-8133-11e8-b851-5319c08f7cee_story.html", 
            "title": "#MeToo, to the president, is little more than a punchline - The ...https://www.washingtonpost.com/...metoo.../7e3d4d3a-8133-11e8-b851-5319c08f7cee_..."
        }, 
        {
            "url": "https://www.huffingtonpost.com/entry/the-me-too-campaign-was-created-by-a-black-woman-10-years-ago_us_59e61a7fe4b02a215b336fee", 
            "title": "The 'Me Too' Campaign Was Created By A Black Woman 10 Years ...https://www.huffingtonpost.com/.../the-me-too-campaign-was-created-by-a-black-wo..."
        }, 
        {
            "url": "https://www.economist.com/business/2018/09/27/american-business-and-metoo", 
            "title": "American business and #MeToo - Behind closed doors - The Economisthttps://www.economist.com/business/2018/09/27/american-business-and-metoo"
        }, 
        {
            "url": "https://mashable.com/category/metoo/", 
            "title": "metoo - Mashablehttps://mashable.com/category/metoo/"
        }, 
        {
            "url": "https://www.vanityfair.com/news/2018/02/monica-lewinsky-in-the-age-of-metoo", 
            "title": "Monica Lewinsky: Emerging from \u201cthe House of Gaslight\u201d in the Age of ...https://www.vanityfair.com/news/2018/02/monica-lewinsky-in-the-age-of-metoo"
        }, 
        {
            "url": "https://www.wnyc.org/shows/beyond-metoo", 
            "title": "Beyond #MeToo | WNYC | New York Public Radio, Podcasts, Live ...https://www.wnyc.org/shows/beyond-metoo"
        }, 
        {
            "url": "https://www.pbs.org/show/metoo-now-what/", 
            "title": "#MeToo, Now What? | PBShttps://www.pbs.org/show/metoo-now-what/"
        }, 
        {
            "url": "https://www.usnews.com/topics/subjects/metoo", 
            "title": "#MeToo | US Newshttps://www.usnews.com/topics/subjects/metoo"
        }
    ], 
    "page_0": [
        {
            "url": "https://metoomvmt.org/", 
            "title": "Me Too Movementhttps://metoomvmt.org/"
        }, 
        {
            "url": "https://en.wikipedia.org/wiki/Me_Too_movement", 
            "title": "Me Too movement - Wikipediahttps://en.wikipedia.org/wiki/Me_Too_movement"
        }, 
        {
            "url": "https://twitter.com/hashtag/metoo", 
            "title": "News about #metoo on Twitterhttps://twitter.com/hashtag/metoo"
        }, 
        {
            "url": "https://en.wikipedia.org/wiki/Me_Too_movement", 
            "title": "Me Too movement - Wikipediahttps://en.wikipedia.org/wiki/Me_Too_movement"
        }, 
        {
            "url": "https://money.cnn.com/2017/12/06/media/time-person-of-the-year-2017/index.html", 
            "title": "Time's Person of the Year 2017 is 'The Silence Breakers' - CNN Moneyhttps://money.cnn.com/2017/12/06/media/time-person-of-the-year.../index.html"
        }, 
        {
            "url": "https://en.wikipedia.org/wiki/Time%27s_Up_(movement)", 
            "title": "Time's Up (movement) - Wikipediahttps://en.wikipedia.org/wiki/Time%27s_Up_(movement)"
        }, 
        {
            "url": "https://www.merriam-webster.com/dictionary/me-too", 
            "title": "Me-too | Definition of Me-too by Merriam-Websterhttps://www.merriam-webster.com/dictionary/me-too"
        }, 
        {
            "url": "https://www.newyorker.com/tag/me-too", 
            "title": "The #MeToo Movement: News and Reporting on Sexual Harassment ...https://www.newyorker.com/tag/me-too"
        }, 
        {
            "url": "https://metoorising.withgoogle.com/", 
            "title": "Me Too Risinghttps://metoorising.withgoogle.com/"
        }, 
        {
            "url": "https://www.nytimes.com/series/metoo-moment", 
            "title": "The #MeToo Moment - The New York Timeshttps://www.nytimes.com/series/metoo-moment"
        }, 
        {
            "url": "http://www.chicagotribune.com/lifestyles/ct-me-too-timeline-20171208-htmlstory.html", 
            "title": "A timeline of events related to the #MeToo movement - Chicago Tribunewww.chicagotribune.com/lifestyles/ct-me-too-timeline-20171208-htmlstory.html"
        }, 
        {
            "url": "https://www.theverge.com/2018/1/15/16893734/metoo-movement-backlash", 
            "title": "Forget the backlash \u2014 we need #MeToo now more than ever - The ...https://www.theverge.com/2018/1/15/16893734/metoo-movement-backlash"
        }, 
        {
            "url": "https://www.newyorker.com/culture/cultural-comment/metoo-itwasme-and-the-post-weinstein-megaphone-of-social-media", 
            "title": "#MeToo, #ItWasMe, and the Post-Weinstein Megaphone of Social ...https://www.newyorker.com/.../metoo-itwasme-and-the-post-weinstein-megaphone-of-so..."
        }
    ], 
    "page_1": [
        {
            "url": "https://twitter.com/metoomvmt?lang=en", 
            "title": "Me Too (@MeTooMVMT) | Twitterhttps://twitter.com/metoomvmt?lang=en"
        }, 
        {
            "url": "https://www.nytimes.com/2018/10/17/world/asia/india-mj-akbar-resigns-metoo.html", 
            "title": "A Top Indian Minister Resigns, but Can #MeToo Reform Government ...https://www.nytimes.com/2018/10/17/world/asia/india-mj-akbar-resigns-metoo.html"
        }, 
        {
            "url": "http://time.com/time-person-of-the-year-2017-silence-breakers/", 
            "title": "TIME Person of the Year 2017: The Silence Breakers | Time.comtime.com/time-person-of-the-year-2017-silence-breakers/"
        }, 
        {
            "url": "https://www.npr.org/tags/570698249/-metoo", 
            "title": "#metoo : NPRhttps://www.npr.org/tags/570698249/-metoo"
        }, 
        {
            "url": "https://www.npr.org/sections/goatsandsoda/2018/10/16/656864272/-metoo-movement-gathers-force-in-india", 
            "title": "MeToo Movement In India Prompts Government Official To Resign - NPRhttps://www.npr.org/sections/goatsandsoda/.../-metoo-movement-gathers-force-in-india"
        }, 
        {
            "url": "https://www.cbsnews.com/news/tarana-burke-bill-clinton-absolutely-an-abuse-of-power-with-monica-lewinksy/", 
            "title": "#MeToo founder says Clinton affair abuse of power: Tarana Burke ...https://www.cbsnews.com/.../tarana-burke-bill-clinton-absolutely-an-abuse-of-power-..."
        }, 
        {
            "url": "https://www.bbc.com/news/world-asia-india-45821100", 
            "title": "MJ Akbar: India minister quits after #MeToo allegations - BBC Newshttps://www.bbc.com/news/world-asia-india-45821100"
        }, 
        {
            "url": "https://www.facebook.com/MeTooMVMT/", 
            "title": "Me Too Movement - #metoo - Home | Facebookhttps://www.facebook.com/MeTooMVMT/"
        }, 
        {
            "url": "https://www.vox.com/identities/2018/10/9/17933746/me-too-movement-metoo-brett-kavanaugh-weinstein", 
            "title": "Brett Kavanaugh, Harvey Weinstein, and the evolution of #MeToo - Voxhttps://www.vox.com/identities/.../me-too-movement-metoo-brett-kavanaugh-weinstei..."
        }, 
        {
            "url": "http://www.chicagotribune.com/lifestyles/ct-me-too-timeline-20171208-htmlstory.html", 
            "title": "A timeline of events related to the #MeToo movement - Chicago Tribunewww.chicagotribune.com/lifestyles/ct-me-too-timeline-20171208-htmlstory.html"
        }
    ], 
    "page_4": [
        {
            "url": "http://metoo.support/", 
            "title": "MeToo Supportmetoo.support/"
        }, 
        {
            "url": "http://www.hollywoodfringe.org/4936", 
            "title": "Hollywood Fringe - #metoowww.hollywoodfringe.org/4936"
        }, 
        {
            "url": "http://justbeinc.wixsite.com/justbeinc/the-me-too-movement-cmml", 
            "title": "justbeinc | The 'me too.' Movement - Wix.comjustbeinc.wixsite.com/justbeinc/the-me-too-movement-cmml"
        }, 
        {
            "url": "https://www.theskimm.com/noexcuses/5jdXdBFRdYUImK6gMSyAc2/MeToo", 
            "title": "#MeToo - theSkimmhttps://www.theskimm.com/noexcuses/5jdXdBFRdYUImK6gMSyAc2/MeToo"
        }, 
        {
            "url": "https://www.glamour.com/metoo", 
            "title": "The MeToo Movement: Continuing the Conversation on Sexual ...https://www.glamour.com/metoo"
        }, 
        {
            "url": "https://www.apnews.com/MeToo", 
            "title": "Associated Press News - MeToohttps://www.apnews.com/MeToo"
        }, 
        {
            "url": "https://www.washingtonexaminer.com/news/media-turn-on-hillary-clinton-after-she-exempts-bill-from-the-metoo-movement", 
            "title": "Media turn on Hillary Clinton after she exempts Bill from the #MeToo ...https://www.washingtonexaminer.com/.../media-turn-on-hillary-clinton-after-she-exe..."
        }, 
        {
            "url": "https://www.newsweek.com/topic/metoo", 
            "title": "#MeToo - Newsweekhttps://www.newsweek.com/topic/metoo"
        }, 
        {
            "url": "https://books.google.com/books?id=T9xoDwAAQBAJ&pg=PA218&lpg=PA218&dq=metoo&source=bl&ots=-DQAp4uN1s&sig=tcfpO6QYEmtUWBURGdfYoB_rsnY&hl=en&sa=X&ved=2ahUKEwjKqrn6ro_eAhXGzlkKHX7tDcA4KBDoATAIegQIARAB", 
            "title": "#MeToo: Women Speak Out Against Sexual Assaulthttps://books.google.com/books?isbn=1642820008"
        }, 
        {
            "url": "https://www.nbcnews.com/news/us-news/year-ago-alyssa-milano-started-conversation-about-metoo-these-women-n920246", 
            "title": "A year ago, Alyssa Milano started a conversation about #MeToo ...https://www.nbcnews.com/.../year-ago-alyssa-milano-started-conversation-about-meto..."
        }
    ]
}