{
    "page_2": [
        {
            "url": "https://prolifelouisiana.org/louisiana-abortion-statistics/", 
            "title": "Louisiana Abortion Statistics | Louisiana Right to Life"
        }, 
        {
            "url": "https://www.lincolndiocese.org/op-ed/legislative-update/11125-2017-abortion-statistics-for-nebraska", 
            "title": "2017 abortion statistics for Nebraska - Diocese of Lincoln"
        }, 
        {
            "url": "http://ncrtl.org/abortion-statistics/", 
            "title": "Abortion Statistics - North Carolina Right to Life"
        }, 
        {
            "url": "https://www.masscitizensforlife.org/abortion-statistics", 
            "title": "Abortion Statistics - Massachusetts Citizens for Life"
        }, 
        {
            "url": "https://www.doh.wa.gov/DataandStatisticalReports/HealthStatistics/AbortionPregnancy", 
            "title": "Abortion/Pregnancy Data - Vital Statistics :: Washington State ..."
        }, 
        {
            "url": "https://www.ncbi.nlm.nih.gov/pmc/articles/PMC1650526/", 
            "title": "Abortion Statistics? - NCBI - NIH"
        }, 
        {
            "url": "https://www.oregon.gov/oha/PH/BirthDeathCertificates/VitalStatistics/Pages/Induced-Abortion-Data.aspx", 
            "title": "Oregon Health Authority : Induced Abortion Data : Vital Statistics ..."
        }, 
        {
            "url": "http://ahca.myflorida.com/MCHQ/Central_Services/Training_Support/Reports.shtml", 
            "title": "AHCA: Central Services: Training and Support Unit"
        }, 
        {
            "url": "http://www.dph.illinois.gov/sites/default/files/publications/illinois-abortion-statistics-2016-121317.pdf", 
            "title": "Illinois Abortion Statistics 2016 - IDPH - Illinois.gov"
        }, 
        {
            "url": "https://www.cosmopolitan.com/politics/a58738/texas-hb2-abortion-statistics/", 
            "title": "7 Eye-Opening Texas Abortion Statistics - Why the Supreme Court ..."
        }
    ], 
    "page_3": [
        {
            "url": "http://www.foxnews.com/story/2003/06/17/fast-facts-us-abortion-statistics.html", 
            "title": "Fast Facts: U.S. Abortion Statistics | Fox News"
        }, 
        {
            "url": "http://www.stjoanofarc.com/abortion-stats", 
            "title": "Abortion Statistics - Saint Joan of Arc Roman Catholic Church ..."
        }, 
        {
            "url": "https://www.michigan.gov/mdhhs/0,5885,7-339-73970_2944_4669_4681---,00.html", 
            "title": "MDHHS - Natality and Pregnancy - State of Michigan"
        }, 
        {
            "url": "https://health.mo.gov/data/abortions/data.php", 
            "title": "Data & Statistical Reports | Abortion Information | Health & Senior ..."
        }, 
        {
            "url": "http://www.usccb.org/issues-and-action/human-life-and-dignity/abortion/current-abortion-statistics.cfm", 
            "title": "Current Abortion Statistics"
        }, 
        {
            "url": "https://www.rtl.org/prolife_issues/abortionstats_us.html", 
            "title": "U.S. Abortion Statistics - Right to Life of Michigan"
        }, 
        {
            "url": "https://www.dshs.texas.gov/chs/vstat/annrpts.shtm", 
            "title": "Texas Department of State Health Services, Vital Statistics Annual ..."
        }, 
        {
            "url": "http://ww1.antiochian.org/node/16950", 
            "title": "Abortion Statistics | Antiochian Orthodox Christian Archdiocese"
        }, 
        {
            "url": "https://illinoisrighttolife.org/2016-illinois-abortion-statistics-il-abortions-drop-to-their-lowest/", 
            "title": "2016 Illinois Abortion Statistics: IL Abortions Drop to their Lowest ..."
        }, 
        {
            "url": "https://www.liveaction.org/news/understanding-abortion-reporting-numbers/", 
            "title": "Six things you should know about how abortion statistics are reported"
        }
    ], 
    "page_0": [
        {
            "url": "http://abort73.com/abortion_facts/us_abortion_statistics/", 
            "title": "Facts About Abortion: U.S. Abortion Statistics"
        }, 
        {
            "url": "https://www.cdc.gov/reproductivehealth/data_stats/abortion.htm", 
            "title": "Abortion | Data and Statistics | Reproductive Health | CDC"
        }, 
        {
            "url": "https://www.cnn.com/2013/09/18/health/abortion-fast-facts/index.html", 
            "title": "Abortion Fast Facts - CNN - CNN.com"
        }, 
        {
            "url": "https://www.all.org/learn/abortion/abortion-statistics/", 
            "title": "Abortion Statistics - All.org"
        }, 
        {
            "url": "https://www.focusonthefamily.com/socialissues/life-issues/dignity-of-human-life/abortion-statistics", 
            "title": "By the Numbers: U.S. Abortion Statistics | Focus on the Family"
        }, 
        {
            "url": "https://en.wikipedia.org/wiki/Abortion_statistics_in_the_United_States", 
            "title": "Abortion statistics in the United States - Wikipedia"
        }, 
        {
            "url": "https://en.wikipedia.org/wiki/Late_termination_of_pregnancy", 
            "title": "Late termination of pregnancy - Wikipedia"
        }, 
        {
            "url": "https://en.wikipedia.org/wiki/Unintended_pregnancy", 
            "title": "Unintended pregnancy - Wikipedia"
        }, 
        {
            "url": "https://en.wikipedia.org/wiki/Abortion_in_the_United_States_by_state", 
            "title": "Abortion in the United States by state - Wikipedia"
        }, 
        {
            "url": "https://en.wikipedia.org/wiki/Abortion_statistics_in_the_United_States", 
            "title": "Abortion statistics in the United States - Wikipedia"
        }, 
        {
            "url": "https://www.guttmacher.org/fact-sheet/induced-abortion-united-states", 
            "title": "Induced Abortion in the United States | Guttmacher Institute"
        }, 
        {
            "url": "https://www.guttmacher.org/united-states/abortion", 
            "title": "United States Abortion | Guttmacher Institute"
        }, 
        {
            "url": "https://nrlc.org/uploads/factsheets/FS01AbortionintheUS.pdf", 
            "title": "ABORTION statistics"
        }, 
        {
            "url": "http://www.slate.com/articles/double_x/doublex/2011/10/most_surprising_abortion_statistic_the_majority_of_women_who_ter.html", 
            "title": "Most surprising abortion statistic: The majority of women who ..."
        }, 
        {
            "url": "https://www.washingtonpost.com/news/fact-checker/wp/2015/08/12/for-planned-parenthood-abortion-stats-3-percent-and-94-percent-are-both-misleading/", 
            "title": "For Planned Parenthood abortion stats, '3 percent' and '94 percent' are ..."
        }, 
        {
            "url": "https://www.cosmopolitan.com/politics/a58738/texas-hb2-abortion-statistics/", 
            "title": "7 Eye-Opening Texas Abortion Statistics - Why the Supreme Court ..."
        }
    ], 
    "page_1": [
        {
            "url": "http://www.worldometers.info/abortions/", 
            "title": "Abortion Statistics - Worldometers"
        }, 
        {
            "url": "http://www.johnstonsarchive.net/policy/abortion/", 
            "title": "Abortion statistics and other data - Johnston's Archive"
        }, 
        {
            "url": "http://www.johnstonsarchive.net/policy/abortion/ab-japan.html", 
            "title": "Historical abortion statistics, Japan - Johnston's Archive"
        }, 
        {
            "url": "https://www.statista.com/topics/3218/abortion-in-the-us/", 
            "title": "Abortion in the U.S. - Statistics & Facts | Statista"
        }, 
        {
            "url": "http://www.slate.com/articles/double_x/doublex/2011/10/most_surprising_abortion_statistic_the_majority_of_women_who_ter.html", 
            "title": "Most surprising abortion statistic: The majority of women who ..."
        }, 
        {
            "url": "https://www.kff.org/womens-health-policy/state-indicator/abortions-by-race/", 
            "title": "Reported Legal Abortions by Race of Woman Who Obtained Abortion ..."
        }, 
        {
            "url": "https://www.kff.org/state-category/womens-health/abortion-statistics-and-policies/", 
            "title": "State Category | Abortion Statistics and Policies | The Henry J. Kaiser ..."
        }, 
        {
            "url": "http://www.numberofabortions.com/", 
            "title": "Number of Abortions in US & Worldwide - Number of abortions since ..."
        }, 
        {
            "url": "https://www.bustle.com/articles/118135-9-must-know-abortion-statistics-that-provide-a-bigger-picture-of-its-accessibility-role-in-society", 
            "title": "9 Must-Know Abortion Statistics That Provide A Bigger Picture Of Its ..."
        }, 
        {
            "url": "http://www.priestsforlife.org/statistics/", 
            "title": "Abortion Statistics - Priests for Life"
        }
    ], 
    "page_4": [
        {
            "url": "https://www.irtl.org/act/indiana-abortion-statistics/", 
            "title": "Indiana Abortion Statistics | Indiana Right To Life"
        }, 
        {
            "url": "https://www.researchgate.net/figure/Official-abortion-statistics-in-Belarus-Russia-and-Ukraine_fig1_233967823", 
            "title": "Official abortion statistics in Belarus, Russia, and Ukraine. | Download ..."
        }, 
        {
            "url": "https://ajph.aphapublications.org/doi/abs/10.2105/AJPH.73.2.217", 
            "title": "Abortion Statistics? | AJPH | Vol. 73 Issue 2"
        }, 
        {
            "url": "http://dhhs.ne.gov/publichealth/Abortion%20Reports/2017%20Statistical%20Report%20of%20Abortions.pdf", 
            "title": "2017 Statistical Report of Abortions - Nebraska Department of Health ..."
        }, 
        {
            "url": "https://www.washingtonpost.com/news/fact-checker/wp/2015/08/12/for-planned-parenthood-abortion-stats-3-percent-and-94-percent-are-both-misleading/", 
            "title": "For Planned Parenthood abortion stats, '3 percent' and '94 percent' are ..."
        }, 
        {
            "url": "https://www.thoughtco.com/abortion-facts-and-statistics-3534189", 
            "title": "Abortion Facts and Statistics in the Millennium - ThoughtCo"
        }, 
        {
            "url": "https://assets.publishing.service.gov.uk/government/uploads/system/uploads/attachment_data/file/714183/2017_Abortion_Statistics_Commentary.pdf", 
            "title": "[PDF]Abortion Statistics, England and Wales: 2017"
        }, 
        {
            "url": "https://www.bound4life.com/statistics/", 
            "title": "Statistics \u2014 Bound4LIFE"
        }, 
        {
            "url": "https://www.lifesitenews.com/tags/tag/abortion+statistics", 
            "title": "Abortion Statistics | LifeSite"
        }, 
        {
            "url": "http://coloradortl.org/issues-policies/colorado-abortion-statistics", 
            "title": "Colorado Abortion Statistics | Colorado Right To Life"
        }
    ]
}