{
    "page_2": [
        {
            "url": "http://www.cnn.com/2014/12/05/opinion/randazza-uva-rape-allegations/index.html", 
            "title": "Should we always believe the victim? (Opinion) - CNN.com"
        }, 
        {
            "url": "https://www.usnews.com/opinion/blogs/economic-intelligence/2013/10/24/statistics-dont-back-up-claims-about-rape-culture", 
            "title": "Statistics Don't Back Up Claims About 'Rape Culture' | Economic ..."
        }, 
        {
            "url": "https://www.counseling.org/docs/default-source/vistas/understanding-rape-myths.pdf?sfvrsn=8", 
            "title": "Understanding Rape Myths - American Counseling Association"
        }, 
        {
            "url": "https://mashable.com/2015/07/08/believing-rape/", 
            "title": "Burden of truth: When no one believes your rape but you - Mashable"
        }, 
        {
            "url": "https://www.belfasttelegraph.co.uk/news/northern-ireland/just-one-in-five-believe-rape-victims-should-not-be-allowed-an-abortion-28786765.html", 
            "title": "Just one in five believe rape victims should not be allowed an abortion ..."
        }, 
        {
            "url": "https://www.jsonline.com/story/news/education/2018/06/19/parents-alec-cook-say-they-believe-women-who-accused-him-rape/715484002/", 
            "title": "Parents of Alec Cook say they believe women who accused him of rape"
        }, 
        {
            "url": "http://www.d.umn.edu/cla/faculty/jhamlin/3925/Readings/PoliceRape.html", 
            "title": "Police Officers' Perceptions Of Rape (Campbell, Rebecca; Camille R ..."
        }, 
        {
            "url": "https://metro.co.uk/2018/04/02/scotland-yard-will-no-longer-automatically-believe-rape-complainants-7435123/", 
            "title": "Scotland Yard will no longer automatically believe rape complainants ..."
        }, 
        {
            "url": "https://thefrisky.com/why-i-believe-conor-obersts-anonymous-rape-accuser/", 
            "title": "Why I Believe Conor Oberst's Anonymous Rape Accuser - The Frisky"
        }, 
        {
            "url": "http://www.debate.org/opinions/does-rape-culture-exist", 
            "title": "Does rape culture exist? | Debate.org"
        }
    ], 
    "page_3": [
        {
            "url": "https://www.safeline.org.uk/", 
            "title": "Safeline - Believe in you - Surviving sexual abuse & rape"
        }, 
        {
            "url": "https://foxync.com/3406272/do-you-believe-the-rape-allegations-against-bill-cosby-poll/", 
            "title": "Do You Believe The Rape Allegations Against Bill Cosby? [POLL ..."
        }, 
        {
            "url": "https://www.thenewsminute.com/article/watch-these-people-believe-rape-consensual-girls-are-also-blame-79236", 
            "title": "Watch: These people believe rape is 'consensual', that girls are also to ..."
        }, 
        {
            "url": "https://www.quora.com/Do-pro-lifers-believe-rape-victims-should-keep-the-children-of-their-rapists", 
            "title": "Do pro-lifers believe rape victims should keep the children of ..."
        }, 
        {
            "url": "https://www.elle.com/culture/career-politics/a13977980/me-too-movement-false-accusations-believe-women/", 
            "title": "Despite What You May Have Heard, \"Believe Women\" Has Never ..."
        }, 
        {
            "url": "https://www.thesun.co.uk/news/5952732/rape-victim-belief-policy-scrapped/", 
            "title": "Cops will no longer 'automatically' believe rape victims, says Met chief"
        }, 
        {
            "url": "http://www.southernct.edu/sexual-misconduct/facts.html", 
            "title": "Rape Culture, Victim Blaming, and The Facts"
        }, 
        {
            "url": "https://www.bustle.com/articles/2675-science-explains-why-people-dont-believe-rape-victims", 
            "title": "Science Explains Why People Don't Believe Rape Victims - Bustle"
        }, 
        {
            "url": "https://www.nsvrc.org/sites/default/files/Publications_NSVRC_Overview_False-Reporting.pdf", 
            "title": "FAlSE REPORtiNG - National Sexual Violence Resource Center"
        }, 
        {
            "url": "http://www.wtva.com/content/news/Nashville-police-looking-for-Lee-County-car-following-rape--492632611.html", 
            "title": "UPDATE: Lee County car no longer believed connected to Nashville ..."
        }
    ], 
    "page_0": [
        {
            "url": "https://www.rainn.org/about-national-sexual-assault-telephone-hotline", 
            "title": "About the National Sexual Assault Telephone Hotline | RAINN"
        }, 
        {
            "url": "https://www.nytimes.com/2018/09/27/us/politics/brett-kavanaugh-confirmation-hearings.html", 
            "title": "Brett Kavanaugh and Christine Blasey Ford Square Off in Emotional ..."
        }, 
        {
            "url": "https://www.telegraph.co.uk/women/life/treating-rape-victims-liars-will-set-british-justice-back-decades/", 
            "title": "Treating rape victims as 'liars' will set British justice back by decades"
        }, 
        {
            "url": "https://www.theguardian.com/lifeandstyle/2018/sep/24/rape-conviction-figures-uk", 
            "title": "Why are we so desperate to believe men in rape cases? | Chitra ..."
        }, 
        {
            "url": "https://en.wikipedia.org/wiki/Rape_culture", 
            "title": "Rape culture - Wikipedia"
        }, 
        {
            "url": "https://bust.com/general/10232-take-that-rape-cuture-science-explains-why-people-dont-believe-rape-victims.html", 
            "title": "Take That, Rape Culture! Science Explains Why People Don't Believe ..."
        }, 
        {
            "url": "https://www.bostonglobe.com/lifestyle/2018/09/24/this-isn-just-about-christine-blasey-ford-end-rape-culture-need-believe-survivors/PHnm1e7OJOp8FXmN0QAOaO/story.html", 
            "title": "This isn't just about Christine Blasey Ford. To end rape culture, we ..."
        }, 
        {
            "url": "https://www.snopes.com/fact-check/personal-foul/", 
            "title": "Republicans on Rape - Snopes.com"
        }, 
        {
            "url": "https://www.snopes.com/fact-check/rape-of-innocents/", 
            "title": "FACT CHECK: Infant Rape Cures AIDS - Snopes.com"
        }
    ], 
    "page_1": [
        {
            "url": "https://www.washingtonpost.com/posteverything/wp/2014/12/06/no-matter-what-jackie-said-we-should-automatically-believe-rape-claims/", 
            "title": "No matter what Jackie said, we should generally believe rape claims ..."
        }, 
        {
            "url": "https://www.vox.com/2016/5/1/11538748/believe-rape-victims", 
            "title": "Rape and sexual assault are common. So why don't we believe ... - Vox"
        }, 
        {
            "url": "https://www.louderwithcrowder.com/juanita-broaddrick-dick-durbin/", 
            "title": "Dem Senator: 'Always Believe Rape Victims.' Juanita Broaddrick ..."
        }, 
        {
            "url": "http://www.slate.com/articles/news_and_politics/jurisprudence/2013/06/why_cops_don_t_believe_rape_victims_and_how_brain_science_can_solve_the.html", 
            "title": "Why cops don't believe rape victims and how brain science can solve ..."
        }, 
        {
            "url": "https://www.irishexaminer.com/breakingnews/specialreports/rape-why-not-believe-the-woman-859885.html", 
            "title": "Rape: Why not believe the woman? | Irish Examiner"
        }, 
        {
            "url": "https://www.huffingtonpost.com/danielle-campoamor/what-happens-when-we-dont_b_7756268.html", 
            "title": "What Happens When We Don't Believe Rape Victims | HuffPost"
        }, 
        {
            "url": "https://elpais.com/elpais/2018/06/06/inenglish/1528277051_276793.html", 
            "title": "Half of Spaniards believe alcohol is \u201coften\u201d to blame for rape - El Pa\u00eds"
        }, 
        {
            "url": "https://www.independent.co.uk/voices/comment/do-we-really-need-scientific-research-to-believe-rape-victims-10467917.html", 
            "title": "Do we really need scientific research to believe rape victims? | The ..."
        }, 
        {
            "url": "https://www.vogue.com/article/bill-cosby-uva-rape-campus-assault", 
            "title": "Bill Cosby, UVA, and Why We Don't Believe Rape Victims - Vogue"
        }, 
        {
            "url": "https://www.businesslive.co.za/bd/opinion/2017-11-01-men-we-too-must-support-and-believe-rape-victims/", 
            "title": "Men, we too must support and believe rape victims - BusinessLIVE"
        }
    ], 
    "page_4": [
        {
            "url": "https://www.odh.ohio.gov/~/media/odh/assets/files/hprr/sexual%20assult/appendix182011.ashx", 
            "title": "When Men Are Raped - Ohio Department of Health"
        }, 
        {
            "url": "http://www.takepart.com/article/2016/08/24/online-comments-sexual-assault", 
            "title": "Only 16 Percent of Internet Commenters Believe Rape Victims | TakePart"
        }, 
        {
            "url": "https://www.goodreads.com/quotes/475720-i-don-t-believe-rape-is-inevitable-or-natural-if-i", 
            "title": "Quote by Andrea Dworkin: \u201cI don't believe rape is inevitable or natural ..."
        }, 
        {
            "url": "https://www.hollywoodreporter.com/news/netflix-fires-exec-who-told-danny-masterson-accuser-we-dont-believe-rape-claims-1066889", 
            "title": "Netflix Fires Exec Who Told Danny Masterson Accuser \"We Don't ..."
        }, 
        {
            "url": "https://psmag.com/news/science-says-believe-women", 
            "title": "Science Says: Believe Women - Pacific Standard"
        }, 
        {
            "url": "https://www.irishtimes.com/opinion/flawed-notion-of-rape-culture-is-lacking-in-logic-1.3283053", 
            "title": "Flawed notion of 'rape culture' is lacking in logic - The Irish Times"
        }, 
        {
            "url": "https://www.chabad.org/parshah/article_cdo/aid/1940448/jewish/Does-the-Torah-Punish-a-Rape-Victim.htm", 
            "title": "Does the Torah Punish a Rape Victim? - Inner Stream - Parshah"
        }, 
        {
            "url": "https://www.rollingstone.com/culture/culture-features/how-police-still-fail-rape-victims-97782/", 
            "title": "How Police Still Fail Rape Victims \u2013 Rolling Stone"
        }, 
        {
            "url": "https://plato.stanford.edu/entries/feminism-rape/", 
            "title": "Feminist Perspectives on Rape (Stanford Encyclopedia of Philosophy)"
        }, 
        {
            "url": "https://womens-studies.rutgers.edu/images/stories/Faculty_Image/Understandingcommunityspecificrapemyths.pdf", 
            "title": "Understanding Community- Specific Rape Myths - Rutgers Women ..."
        }
    ]
}